{
    "data": "[{\"view_history\":\"[{\\\"page_index\\\":0,\\\"viewing_time\\\":2663}]\",\"rt\":2663,\"trialid\":\"Instructions_MR_01\",\"trial_type\":\"instructions\",\"trial_index\":0,\"time_elapsed\":2665,\"internal_node_id\":\"0.0-0.0\"},{\"view_history\":\"[{\\\"page_index\\\":0,\\\"viewing_time\\\":958}]\",\"rt\":958,\"trialid\":\"Instructions_MR_02\",\"trial_type\":\"instructions\",\"trial_index\":1,\"time_elapsed\":3624,\"internal_node_id\":\"0.0-1.0\"},{\"rt\":19275,\"responses\":\"{\\\"Q0\\\":[\\\"<br /><img src='img/pag1_3_2.png' />\\\",\\\"<br /><img src='img/pag1_3_3.png' />\\\"]}\",\"trialid\":\"MR_Test1\",\"trial_type\":\"survey-multi-selectmr\",\"trial_index\":2,\"time_elapsed\":22904,\"internal_node_id\":\"0.0-2.0\"},{\"rt\":2324,\"responses\":\"{\\\"Q0\\\":[\\\"<br /><img src='img/pag2_1_1.png' />\\\",\\\"<br /><img src='img/pag2_1_2.png' />\\\"]}\",\"trialid\":\"MR_Test2_a\",\"trial_type\":\"survey-multi-selectmr\",\"trial_index\":3,\"time_elapsed\":25231,\"internal_node_id\":\"0.0-3.0\"},{\"rt\":2132,\"responses\":\"{\\\"Q0\\\":[\\\"<br /><img src='img/pag2_2_3.png' />\\\",\\\"<br /><img src='img/pag2_2_4.png' />\\\"]}\",\"trialid\":\"MR_Test2_b\",\"trial_type\":\"survey-multi-selectmr\",\"trial_index\":4,\"time_elapsed\":27367,\"internal_node_id\":\"0.0-4.0\"},{\"rt\":2260,\"responses\":\"{\\\"Q0\\\":[\\\"<br /><img src='img/pag2_3_1.png' />\\\",\\\"<br /><img src='img/pag2_3_4.png' />\\\"]}\",\"trialid\":\"MR_Test2_c\",\"trial_type\":\"survey-multi-selectmr\",\"trial_index\":5,\"time_elapsed\":29631,\"internal_node_id\":\"0.0-5.0\"},{\"rt\":2540,\"responses\":\"{\\\"Q0\\\":[\\\"<br /><img src='img/pag3_1_2.png' />\\\",\\\"<br /><img src='img/pag3_1_4.png' />\\\"]}\",\"trialid\":\"MR_Trial1_a\",\"trial_type\":\"survey-multi-selectmr\",\"trial_index\":6,\"time_elapsed\":32174,\"internal_node_id\":\"0.0-6.0-0.0\"},{\"rt\":3364,\"responses\":\"{\\\"Q0\\\":[\\\"<br /><img src='img/pag3_2_1.png' />\\\",\\\"<br /><img src='img/pag3_2_3.png' />\\\"]}\",\"trialid\":\"MR_Trial1_b\",\"trial_type\":\"survey-multi-selectmr\",\"trial_index\":7,\"time_elapsed\":35543,\"internal_node_id\":\"0.0-7.0-0.0\"},{\"rt\":3236,\"responses\":\"{\\\"Q0\\\":[\\\"<br /><img src='img/pag3_3_1.png' />\\\",\\\"<br /><img src='img/pag3_3_2.png' />\\\"]}\",\"trialid\":\"MR_Trial1_c\",\"trial_type\":\"survey-multi-selectmr\",\"trial_index\":8,\"time_elapsed\":38782,\"internal_node_id\":\"0.0-8.0-0.0\"},{\"rt\":9998,\"trialid\":\"MR_Trial1_d\",\"trial_type\":\"survey-multi-selectmr\",\"trial_index\":9,\"time_elapsed\":39633,\"internal_node_id\":\"0.0-9.0-0.0\"},{\"rt\":3,\"trialid\":\"MR_Trial1_e\",\"trial_type\":\"survey-multi-selectmr\",\"trial_index\":10,\"time_elapsed\":39640,\"internal_node_id\":\"0.0-10.0-0.0\"},{\"rt\":3,\"trialid\":\"MR_Trial1_f\",\"trial_type\":\"survey-multi-selectmr\",\"trial_index\":11,\"time_elapsed\":39647,\"internal_node_id\":\"0.0-11.0-0.0\"},{\"rt\":2565,\"responses\":\"{\\\"Q0\\\":[\\\"<br /><img src='img/pag4_1_2.png' />\\\",\\\"<br /><img src='img/pag4_1_3.png' />\\\"]}\",\"trialid\":\"MR_Trial2_a\",\"trial_type\":\"survey-multi-selectmr\",\"trial_index\":12,\"time_elapsed\":42214,\"internal_node_id\":\"0.0-12.0-0.0\"},{\"rt\":4998,\"trialid\":\"MR_Trial2_b\",\"trial_type\":\"survey-multi-selectmr\",\"trial_index\":13,\"time_elapsed\":44648,\"internal_node_id\":\"0.0-13.0-0.0\"},{\"rt\":3,\"trialid\":\"MR_Trial2_c\",\"trial_type\":\"survey-multi-selectmr\",\"trial_index\":14,\"time_elapsed\":44654,\"internal_node_id\":\"0.0-14.0-0.0\"},{\"rt\":3,\"trialid\":\"MR_Trial2_d\",\"trial_type\":\"survey-multi-selectmr\",\"trial_index\":15,\"time_elapsed\":44662,\"internal_node_id\":\"0.0-15.0-0.0\"},{\"rt\":6,\"trialid\":\"MR_Trial2_e\",\"trial_type\":\"survey-multi-selectmr\",\"trial_index\":16,\"time_elapsed\":44674,\"internal_node_id\":\"0.0-16.0-0.0\"},{\"rt\":6,\"trialid\":\"MR_Trial2_f\",\"trial_type\":\"survey-multi-selectmr\",\"trial_index\":17,\"time_elapsed\":44690,\"internal_node_id\":\"0.0-17.0-0.0\"},{\"rt\":2345,\"responses\":\"{\\\"Q0\\\":[\\\"<br /><img src='img/pag5_1_2.png' />\\\",\\\"<br /><img src='img/pag5_1_3.png' />\\\"]}\",\"trialid\":\"MR_Trial3_a\",\"trial_type\":\"survey-multi-selectmr\",\"trial_index\":18,\"time_elapsed\":47038,\"internal_node_id\":\"0.0-18.0-0.0\"},{\"rt\":2132,\"responses\":\"{\\\"Q0\\\":[\\\"<br /><img src='img/pag5_2_3.png' />\\\",\\\"<br /><img src='img/pag5_2_4.png' />\\\"]}\",\"trialid\":\"MR_Trial3_b\",\"trial_type\":\"survey-multi-selectmr\",\"trial_index\":19,\"time_elapsed\":49174,\"internal_node_id\":\"0.0-19.0-0.0\"},{\"rt\":4997,\"trialid\":\"MR_Trial3_c\",\"trial_type\":\"survey-multi-selectmr\",\"trial_index\":20,\"time_elapsed\":49691,\"internal_node_id\":\"0.0-20.0-0.0\"},{\"rt\":3,\"trialid\":\"MR_Trial3_d\",\"trial_type\":\"survey-multi-selectmr\",\"trial_index\":21,\"time_elapsed\":49697,\"internal_node_id\":\"0.0-21.0-0.0\"},{\"rt\":3,\"trialid\":\"MR_Trial3_e\",\"trial_type\":\"survey-multi-selectmr\",\"trial_index\":22,\"time_elapsed\":49703,\"internal_node_id\":\"0.0-22.0-0.0\"},{\"rt\":3,\"trialid\":\"MR_Trial3_f\",\"trial_type\":\"survey-multi-selectmr\",\"trial_index\":23,\"time_elapsed\":49709,\"internal_node_id\":\"0.0-23.0-0.0\"},{\"rt\":1660,\"responses\":\"{\\\"Q0\\\":[\\\"<br /><img src='img/pag6_1_2.png' />\\\",\\\"<br /><img src='img/pag6_1_3.png' />\\\"]}\",\"trialid\":\"MR_Trial4_a\",\"trial_type\":\"survey-multi-selectmr\",\"trial_index\":24,\"time_elapsed\":51374,\"internal_node_id\":\"0.0-24.0-0.0\"},{\"rt\":2435,\"responses\":\"{\\\"Q0\\\":[\\\"<br /><img src='img/pag6_2_2.png' />\\\",\\\"<br /><img src='img/pag6_2_3.png' />\\\"]}\",\"trialid\":\"MR_Trial4_b\",\"trial_type\":\"survey-multi-selectmr\",\"trial_index\":25,\"time_elapsed\":53814,\"internal_node_id\":\"0.0-25.0-0.0\"},{\"rt\":4998,\"trialid\":\"MR_Trial4_c\",\"trial_type\":\"survey-multi-selectmr\",\"trial_index\":26,\"time_elapsed\":54712,\"internal_node_id\":\"0.0-26.0-0.0\"},{\"rt\":4,\"trialid\":\"MR_Trial4_d\",\"trial_type\":\"survey-multi-selectmr\",\"trial_index\":27,\"time_elapsed\":54720,\"internal_node_id\":\"0.0-27.0-0.0\"},{\"rt\":2,\"trialid\":\"MR_Trial4_e\",\"trial_type\":\"survey-multi-selectmr\",\"trial_index\":28,\"time_elapsed\":54725,\"internal_node_id\":\"0.0-28.0-0.0\"},{\"rt\":2,\"trialid\":\"MR_Trial4_f\",\"trial_type\":\"survey-multi-selectmr\",\"trial_index\":29,\"time_elapsed\":54730,\"internal_node_id\":\"0.0-29.0-0.0\"}]"
}